hack4u/__init__.py
hack4u/courses.py
hack4u/utils.py
ant0devHack4u-0.1.0.dist-info/METADATA
ant0devHack4u-0.1.0.dist-info/WHEEL
ant0devHack4u-0.1.0.dist-info/top_level.txt
ant0devHack4u-0.1.0.dist-info/RECORD
