Metadata-Version: 2.1
Name: ant0devHack4u
Version: 0.1.0
Summary: Una biblioteca del curso Python Ofensivo de Hack4u
Home-page: https://hack4u.io
Author: Antonio Infantes
